{"link":"/Fragenkatalog/2.1.02","text":"Verhalten gegenüber Fußgängern","number":"2.1.02","questions":[{"link":"/Fragenkatalog/2.1.02-002","text":"Sie fahren auf einer schmalen Straße. Etwa 20 m vor Ihnen läuft plötzlich ein Kind auf die Fahrbahn. Wann ist ein Zusammenprall trotz Gefahrbremsung unvermeidbar?","number":"2.1.02-002","type":"simple","medialink":"","incorrectAnswers":["30 km/h","20 km/h"],"correctAnswers":["50 km/h"]},{"link":"/Fragenkatalog/2.1.02-003","text":"Warum müssen Sie bremsen?","number":"2.1.02-003","type":"video","medialink":"https://www.fuehrerschein-lernsystem.de/videos/iOS/Low/2_1_02_003.mp4","incorrectAnswers":["Weil Fahrgäste aus der Straßenbahn steigen","Weil der Lkw auf meinen Fahrstreifen wechselt"],"correctAnswers":["Weil eine Person auf die Straße läuft"]}]}